pypep/__init__.py
pypep/client.py
pypep/compat.py
pypep_pepco-0.1.0.dist-info/LICENSE
pypep_pepco-0.1.0.dist-info/METADATA
pypep_pepco-0.1.0.dist-info/WHEEL
pypep_pepco-0.1.0.dist-info/top_level.txt
pypep_pepco-0.1.0.dist-info/RECORD
