Metadata-Version: 2.1
Name: pypep-pepco
Version: 0.1.0
Summary: Python SDK for Pasargad Internet Payment Gateway
Home-page: https://github.com/pepco-api/python-rest-sdk 
Author: Reza Seyf
Author-email: rseyf@hotmail.com
License: Apache-2
Platform: UNKNOWN
Classifier: Development Status :: 5 - Production/Stable
Classifier: Intended Audience :: Developers
Classifier: License :: OSI Approved :: Apache Software License
Classifier: Operating System :: OS Independent
Classifier: Programming Language :: Python
Classifier: Programming Language :: Python :: 2
Classifier: Programming Language :: Python :: 2.7
Classifier: Programming Language :: Python :: 3
Classifier: Programming Language :: Python :: 3.5
Classifier: Programming Language :: Python :: 3.6
Classifier: Topic :: Software Development :: Libraries :: Python Modules
License-File: LICENSE
